laba44/__init__.py
laba44/math_advanced/__init__.py
laba44/math_advanced/mul_div.py
laba44/math_basic/__init__.py
laba44/math_basic/add_sub.py
laba44-0.1.0.dist-info/METADATA
laba44-0.1.0.dist-info/WHEEL
laba44-0.1.0.dist-info/top_level.txt
laba44-0.1.0.dist-info/RECORD
