Metadata-Version: 2.4
Name: laba44
Version: 0.1.0
Summary: Учебная Python-библиотека для лабораторной работы №44
Home-page: https://github.com/yourusername/laba44
Author: Your Name
Classifier: Programming Language :: Python :: 3
Classifier: License :: OSI Approved :: MIT License
Classifier: Operating System :: OS Independent
Requires-Python: >=3.8
Dynamic: author
Dynamic: classifier
Dynamic: home-page
Dynamic: requires-python
Dynamic: summary
